pushikoo_adapter_testpusher/__init__.py
pushikoo_adapter_testpusher/api.py
pushikoo_adapter_testpusher/config.py
pushikoo_adapter_testpusher/main.py
pushikoo_adapter_testpusher-0.1.1.dist-info/METADATA
pushikoo_adapter_testpusher-0.1.1.dist-info/WHEEL
pushikoo_adapter_testpusher-0.1.1.dist-info/entry_points.txt
pushikoo_adapter_testpusher-0.1.1.dist-info/licenses/LICENSE
pushikoo_adapter_testpusher-0.1.1.dist-info/RECORD
