Metadata-Version: 2.4
Name: pushikoo-adapter-testpusher
Version: 0.1.1
Summary: TestPusher for pushikoo-adapter development as a template.
Project-URL: Homepage, https://github.com/Pushikoo/pushikoo-adapter-testpusher
Author: Pushikoo
License-File: LICENSE
Classifier: Operating System :: OS Independent
Classifier: Programming Language :: Python :: 3
Requires-Python: >=3.10
Requires-Dist: loguru
Requires-Dist: pushikoo-interface>=0.3.0
Requires-Dist: requests
Provides-Extra: dev
Requires-Dist: pytest; extra == 'dev'
Requires-Dist: ruff; extra == 'dev'
